[
{ "seq_id" : 4, "qsl_idx" : 1118, "data" : "2702000000000000" },
{ "seq_id" : 5, "qsl_idx" : 25998, "data" : "5300000000000000" },
{ "seq_id" : 6, "qsl_idx" : 1622, "data" : "2E00000000000000" },
{ "seq_id" : 7, "qsl_idx" : 24919, "data" : "B501000000000000" },
{ "seq_id" : 0, "qsl_idx" : 29000, "data" : "2301000000000000" },
{ "seq_id" : 1, "qsl_idx" : 34991, "data" : "E000000000000000" },
{ "seq_id" : 2, "qsl_idx" : 42270, "data" : "3803000000000000" },
{ "seq_id" : 3, "qsl_idx" : 24692, "data" : "A701000000000000" },
{ "seq_id" : 60, "qsl_idx" : 31502, "data" : "E802000000000000" },
{ "seq_id" : 61, "qsl_idx" : 3353, "data" : "C300000000000000" },
{ "seq_id" : 62, "qsl_idx" : 5580, "data" : "6703000000000000" },
{ "seq_id" : 63, "qsl_idx" : 43630, "data" : "8800000000000000" },
{ "seq_id" : 52, "qsl_idx" : 48742, "data" : "4001000000000000" },
{ "seq_id" : 53, "qsl_idx" : 23519, "data" : "6C00000000000000" },
{ "seq_id" : 54, "qsl_idx" : 27120, "data" : "0501000000000000" },
{ "seq_id" : 55, "qsl_idx" : 13536, "data" : "B001000000000000" },
{ "seq_id" : 100, "qsl_idx" : 9968, "data" : "A003000000000000" },
{ "seq_id" : 101, "qsl_idx" : 42188, "data" : "C101000000000000" },
{ "seq_id" : 102, "qsl_idx" : 46924, "data" : "1503000000000000" },
{ "seq_id" : 103, "qsl_idx" : 17366, "data" : "9B03000000000000" },
{ "seq_id" : 56, "qsl_idx" : 1555, "data" : "0C00000000000000" },
{ "seq_id" : 57, "qsl_idx" : 19032, "data" : "7400000000000000" },
{ "seq_id" : 58, "qsl_idx" : 44509, "data" : "C301000000000000" },
{ "seq_id" : 59, "qsl_idx" : 26407, "data" : "D503000000000000" },
{ "seq_id" : 68, "qsl_idx" : 46723, "data" : "4801000000000000" },
{ "seq_id" : 69, "qsl_idx" : 18438, "data" : "2F03000000000000" },
{ "seq_id" : 70, "qsl_idx" : 8754, "data" : "1C01000000000000" },
{ "seq_id" : 71, "qsl_idx" : 6492, "data" : "1402000000000000" },
{ "seq_id" : 92, "qsl_idx" : 41550, "data" : "BF00000000000000" },
{ "seq_id" : 93, "qsl_idx" : 25064, "data" : "0B01000000000000" },
{ "seq_id" : 94, "qsl_idx" : 27868, "data" : "1E00000000000000" },
{ "seq_id" : 95, "qsl_idx" : 30713, "data" : "5F03000000000000" },
{ "seq_id" : 48, "qsl_idx" : 13090, "data" : "F401000000000000" },
{ "seq_id" : 49, "qsl_idx" : 5930, "data" : "0E00000000000000" },
{ "seq_id" : 50, "qsl_idx" : 34541, "data" : "1F00000000000000" },
{ "seq_id" : 51, "qsl_idx" : 840, "data" : "A602000000000000" },
{ "seq_id" : 88, "qsl_idx" : 6497, "data" : "6E01000000000000" },
{ "seq_id" : 89, "qsl_idx" : 14504, "data" : "7001000000000000" },
{ "seq_id" : 90, "qsl_idx" : 49525, "data" : "8A02000000000000" },
{ "seq_id" : 91, "qsl_idx" : 36177, "data" : "6001000000000000" },
{ "seq_id" : 96, "qsl_idx" : 39541, "data" : "8303000000000000" },
{ "seq_id" : 97, "qsl_idx" : 42793, "data" : "DD03000000000000" },
{ "seq_id" : 98, "qsl_idx" : 30913, "data" : "AB03000000000000" },
{ "seq_id" : 99, "qsl_idx" : 42611, "data" : "A902000000000000" },
{ "seq_id" : 204, "qsl_idx" : 35584, "data" : "0201000000000000" },
{ "seq_id" : 205, "qsl_idx" : 38755, "data" : "C703000000000000" },
{ "seq_id" : 206, "qsl_idx" : 18964, "data" : "8202000000000000" },
{ "seq_id" : 207, "qsl_idx" : 23339, "data" : "B800000000000000" },
{ "seq_id" : 192, "qsl_idx" : 16123, "data" : "3A00000000000000" },
{ "seq_id" : 193, "qsl_idx" : 21539, "data" : "0301000000000000" },
{ "seq_id" : 194, "qsl_idx" : 41502, "data" : "CE00000000000000" },
{ "seq_id" : 195, "qsl_idx" : 17398, "data" : "4B00000000000000" },
{ "seq_id" : 160, "qsl_idx" : 11744, "data" : "7903000000000000" },
{ "seq_id" : 161, "qsl_idx" : 21640, "data" : "7303000000000000" },
{ "seq_id" : 162, "qsl_idx" : 38957, "data" : "6503000000000000" },
{ "seq_id" : 163, "qsl_idx" : 8830, "data" : "2403000000000000" },
{ "seq_id" : 184, "qsl_idx" : 32189, "data" : "A302000000000000" },
{ "seq_id" : 185, "qsl_idx" : 32481, "data" : "BD02000000000000" },
{ "seq_id" : 186, "qsl_idx" : 31260, "data" : "8003000000000000" },
{ "seq_id" : 187, "qsl_idx" : 28213, "data" : "F800000000000000" },
{ "seq_id" : 180, "qsl_idx" : 3759, "data" : "0302000000000000" },
{ "seq_i

...

l_idx" : 32940, "data" : "BC03000000000000" },
{ "seq_id" : 49934, "qsl_idx" : 30287, "data" : "7803000000000000" },
{ "seq_id" : 49935, "qsl_idx" : 8183, "data" : "8D01000000000000" },
{ "seq_id" : 49952, "qsl_idx" : 28054, "data" : "5602000000000000" },
{ "seq_id" : 49953, "qsl_idx" : 25058, "data" : "EA00000000000000" },
{ "seq_id" : 49954, "qsl_idx" : 15514, "data" : "CC01000000000000" },
{ "seq_id" : 49955, "qsl_idx" : 13204, "data" : "6303000000000000" },
{ "seq_id" : 49856, "qsl_idx" : 13900, "data" : "9200000000000000" },
{ "seq_id" : 49857, "qsl_idx" : 6771, "data" : "0102000000000000" },
{ "seq_id" : 49858, "qsl_idx" : 26797, "data" : "6B02000000000000" },
{ "seq_id" : 49859, "qsl_idx" : 23885, "data" : "0701000000000000" },
{ "seq_id" : 49940, "qsl_idx" : 26738, "data" : "6D01000000000000" },
{ "seq_id" : 49941, "qsl_idx" : 44870, "data" : "9A02000000000000" },
{ "seq_id" : 49942, "qsl_idx" : 37518, "data" : "1203000000000000" },
{ "seq_id" : 49943, "qsl_idx" : 19500, "data" : "9901000000000000" },
{ "seq_id" : 49956, "qsl_idx" : 5224, "data" : "C603000000000000" },
{ "seq_id" : 49957, "qsl_idx" : 22811, "data" : "D403000000000000" },
{ "seq_id" : 49958, "qsl_idx" : 47285, "data" : "E602000000000000" },
{ "seq_id" : 49959, "qsl_idx" : 20957, "data" : "7000000000000000" },
{ "seq_id" : 49972, "qsl_idx" : 23427, "data" : "AA00000000000000" },
{ "seq_id" : 49973, "qsl_idx" : 11831, "data" : "2203000000000000" },
{ "seq_id" : 49974, "qsl_idx" : 36901, "data" : "5503000000000000" },
{ "seq_id" : 49975, "qsl_idx" : 10154, "data" : "3000000000000000" },
{ "seq_id" : 49964, "qsl_idx" : 2854, "data" : "4C00000000000000" },
{ "seq_id" : 49965, "qsl_idx" : 39322, "data" : "A003000000000000" },
{ "seq_id" : 49966, "qsl_idx" : 16121, "data" : "3303000000000000" },
{ "seq_id" : 49967, "qsl_idx" : 28739, "data" : "A903000000000000" },
{ "seq_id" : 49984, "qsl_idx" : 41168, "data" : "2A00000000000000" },
{ "seq_id" : 49985, "qsl_idx" : 157, "data" : "FB02000000000000" },
{ "seq_id" : 49986, "qsl_idx" : 45248, "data" : "0301000000000000" },
{ "seq_id" : 49987, "qsl_idx" : 48738, "data" : "AC01000000000000" },
{ "seq_id" : 49976, "qsl_idx" : 30951, "data" : "D302000000000000" },
{ "seq_id" : 49977, "qsl_idx" : 31912, "data" : "0900000000000000" },
{ "seq_id" : 49978, "qsl_idx" : 8213, "data" : "F400000000000000" },
{ "seq_id" : 49979, "qsl_idx" : 22856, "data" : "AA00000000000000" },
{ "seq_id" : 49968, "qsl_idx" : 4162, "data" : "4B00000000000000" },
{ "seq_id" : 49969, "qsl_idx" : 3208, "data" : "BC01000000000000" },
{ "seq_id" : 49970, "qsl_idx" : 21557, "data" : "A301000000000000" },
{ "seq_id" : 49971, "qsl_idx" : 12270, "data" : "6900000000000000" },
{ "seq_id" : 49960, "qsl_idx" : 33020, "data" : "3901000000000000" },
{ "seq_id" : 49961, "qsl_idx" : 38327, "data" : "B900000000000000" },
{ "seq_id" : 49962, "qsl_idx" : 24918, "data" : "BB01000000000000" },
{ "seq_id" : 49963, "qsl_idx" : 45895, "data" : "8A01000000000000" },
{ "seq_id" : 49988, "qsl_idx" : 22108, "data" : "EF00000000000000" },
{ "seq_id" : 49989, "qsl_idx" : 26608, "data" : "F102000000000000" },
{ "seq_id" : 49990, "qsl_idx" : 21388, "data" : "0501000000000000" },
{ "seq_id" : 49991, "qsl_idx" : 19728, "data" : "5301000000000000" },
{ "seq_id" : 49980, "qsl_idx" : 38815, "data" : "6F01000000000000" },
{ "seq_id" : 49981, "qsl_idx" : 35941, "data" : "DB02000000000000" },
{ "seq_id" : 49982, "qsl_idx" : 47205, "data" : "9601000000000000" },
{ "seq_id" : 49983, "qsl_idx" : 531, "data" : "F201000000000000" },
{ "seq_id" : 49992, "qsl_idx" : 25961, "data" : "8102000000000000" },
{ "seq_id" : 49993, "qsl_idx" : 38797, "data" : "8B00000000000000" },
{ "seq_id" : 49994, "qsl_idx" : 12955, "data" : "E901000000000000" },
{ "seq_id" : 49995, "qsl_idx" : 20878, "data" : "7203000000000000" },
{ "seq_id" : 49996, "qsl_idx" : 44978, "data" : "FC02000000000000" },
{ "seq_id" : 49997, "qsl_idx" : 33704, "data" : "4D00000000000000" },
{ "seq_id" : 49998, "qsl_idx" : 7997, "data" : "1B00000000000000" },
{ "seq_id" : 49999, "qsl_idx" : 40686, "data" : "EA02000000000000" }
]
